kgt/__about__.py
kgt/__about__.pyi
kgt/__init__.py
kgt/__init__.pyi
kgt/_cached.py
kgt/_cached.pyi
kgt/_exceptions.py
kgt/_exceptions.pyi
kgt/_helpers.py
kgt/_helpers.pyi
kgt/_main.py
kgt/_main.pyi
kgt/_offline.py
kgt/_offline.pyi
kgt/_online.py
kgt/_online.pyi
kgt/_unlock.py
kgt/_unlock.pyi
kgt/py.typed
kgt-0.4.7.dist-info/METADATA
kgt-0.4.7.dist-info/WHEEL
kgt-0.4.7.dist-info/top_level.txt
kgt-0.4.7.dist-info/RECORD
