Metadata-Version: 2.1
Name: kgt
Version: 0.4.7
Summary: Python tools for Keygen.sh licensing
Author-email: Nico Schlömer <nico.schloemer@gmail.com>
Project-URL: Homepage, https://github.com/nschloe/kgt
Classifier: Development Status :: 4 - Beta
Classifier: License :: Other/Proprietary License
Classifier: Operating System :: OS Independent
Classifier: Programming Language :: Python
Classifier: Programming Language :: Python :: 3
Classifier: Programming Language :: Python :: 3.7
Classifier: Programming Language :: Python :: 3.8
Classifier: Programming Language :: Python :: 3.9
Classifier: Programming Language :: Python :: 3.10
Classifier: Topic :: Utilities
Requires-Python: >=3.7
Requires-Dist: x21 (>=0.3.3,<0.4.0)
Requires-Dist: appdirs
Requires-Dist: cryptography
Requires-Dist: PyNaCl
Requires-Dist: requests
Requires-Dist: rich
Requires-Dist: tomli
Requires-Dist: tomli-w
